azure/__init__.py
azure/monitor/__init__.py
azure/monitor/events/__init__.py
azure/monitor/events/extension/__init__.py
azure/monitor/events/extension/_events.py
azure/monitor/events/extension/_version.py
azure_monitor_events_extension-0.1.0.dist-info/LICENSE
azure_monitor_events_extension-0.1.0.dist-info/METADATA
azure_monitor_events_extension-0.1.0.dist-info/WHEEL
azure_monitor_events_extension-0.1.0.dist-info/top_level.txt
azure_monitor_events_extension-0.1.0.dist-info/RECORD
